_phashmap.cpython-37m-x86_64-linux-gnu.so
phashmap-0.0.4.dist-info/WHEEL
phashmap-0.0.4.dist-info/top_level.txt
phashmap-0.0.4.dist-info/LICENSE
phashmap-0.0.4.dist-info/METADATA
phashmap-0.0.4.dist-info/RECORD
phashmap/__init__.py
phashmap/type_gen.py
phashmap/phashmap_types_generated.py
phashmap/phashmap_types.py
phashmap/phashmap.py
