Metadata-Version: 2.1
Name: phashmap
Version: 0.0.4
Summary: A Vectorized Dictionary for Python
Home-page: https://github.com/atom-moyer/getpy
Author: yojeep
Author-email: 1379690602@qq.com
Classifier: Programming Language :: Python :: 3
Classifier: Programming Language :: C++
Classifier: Topic :: Scientific/Engineering
Classifier: Topic :: Software Development
Classifier: License :: OSI Approved :: MIT License
License-File: LICENSE
